autumn/workspace/labs/Lab2-SigGen-main/task3/ram2ports.sv
module ram2ports #(
    parameter   ADDRESS_WIDTH = 9,
                DATA_WIDTH = 8
)(
    input logic                     clk,
    input logic                     wr_en,
    input logic                     rd_en,
    input logic [ADDRESS_WIDTH-1:0] wr_addr,
    input logic [ADDRESS_WIDTH-1:0] rd_addr,
    input logic [DATA_WIDTH-1:0] din,
    output logic [DATA_WIDTH-1:0] dout
);

logic [DATA_WIDTH-1:0] ram_array [2**ADDRESS_WIDTH-1:0];

always_ff @(posedge clk) begin
    if (wr_en == 1'b1)
        ram_array[wr_addr] <= din;
    if (rd_en == 1'b1)
        //output is synchronous
        dout <= ram_array [rd_addr];
end
endmodule

autumn/workspace/labs/Lab2-SigGen-main/task3/counter.sv
module counter #(
    parameter WIDTH = 9
)(

    input logic clk,  //clock
    input logic rst,  //reset
    input logic en,   //counter enable 
    input logic  [WIDTH-1:0] incr,
    output logic [WIDTH-1:0] count //count output
);

always_ff @ (posedge clk) begin
    if (rst) 
        count <= 0 ;
    else if (en)
        count <= count + incr; //chagned so not just adding 1 but adding anything
end

endmodule

autumn/workspace/labs/Lab2-SigGen-main/task3/sigdelay.sv
module sigdelay #(
    parameter A_WIDTH = 9,
    parameter D_WIDTH = 8
)(
    //interface signals
    input logic               clk, //clock
    input logic               rst,  //reset
    input logic               wr,   //write enable
    input logic               rd,   //read enable  
    input logic [A_WIDTH-1:0] mic_signal, //data in  
    input logic [A_WIDTH-1:0] offset, //address offset  
    input logic [D_WIDTH-1:0] incr, //increment for addr counter
    output logic [D_WIDTH-1:0] delayed_signal //output data wave
);

    logic [A_WIDTH-1:0]  address; //interconnect wire

counter addrCounter (
    .clk(clk),
    .rst(rst),
    .en(wr),
    .incr(incr),
    .count(address)
);

ram2ports audioRam (
    .clk(clk),
    .wr_en(wr),
    .rd_en(rd),
    .wr_addr(address),
    .rd_addr(address+offset),
    .din(mic_signal),
    .dout(delayed_signal)
);

endmodule

autumn/workspace/labs/Lab2-SigGen-main/task3/sigdelay.vcd
$version Generated by VerilatedVcd $end
$timescale 1ps $end
 $scope module TOP $end
  $var wire 1 # clk $end
  $var wire 1 $ rst $end
  $var wire 1 % wr $end
  $var wire 1 & rd $end
  $var wire 9 ' mic_signal [8:0] $end
  $var wire 9 ( offset [8:0] $end
  $var wire 8 ) incr [7:0] $end
  $var wire 8 * delayed_signal [7:0] $end
  $scope module sigdelay $end
   $var wire 32 / A_WIDTH [31:0] $end
   $var wire 32 0 D_WIDTH [31:0] $end
   $var wire 1 # clk $end
   $var wire 1 $ rst $end
   $var wire 1 % wr $end
   $var wire 1 & rd $end
   $var wire 9 ' mic_signal [8:0] $end
   $var wire 9 ( offset [8:0] $end
   $var wire 8 ) incr [7:0] $end
   $var wire 8 * delayed_signal [7:0] $end
   $var wire 9 + address [8:0] $end
   $scope module addrCounter $end
    $var wire 32 / WIDTH [31:0] $end
    $var wire 1 # clk $end
    $var wire 1 $ rst $end
    $var wire 1 % en $end
    $var wire 9 , incr [8:0] $end
    $var wire 9 + count [8:0] $end
   $upscope $end
   $scope module audioRam $end
    $var wire 32 / ADDRESS_WIDTH [31:0] $end
    $var wire 32 0 DATA_WIDTH [31:0] $end
    $var wire 1 # clk $end
    $var wire 1 % wr_en $end
    $var wire 1 & rd_en $end
    $var wire 9 + wr_addr [8:0] $end
    $var wire 9 - rd_addr [8:0] $end
    $var wire 8 . din [7:0] $end
    $var wire 8 * dout [7:0] $end
   $upscope $end
  $upscope $end
 $upscope $end
$enddefinitions $end


#0
1#
0$
1%
1&
b000000000 '
b001000000 (
b00000000 )
b00000000 *
b000000000 +
b000000000 ,
b001000000 -
b00000000 .
b00000000000000000000000000001001 /
b00000000000000000000000000001000 0
#1
0#
#2
1#
b001100100 '
b000000001 (
b000000001 -
b01100100 .
#3
0#
#4
1#
b001011111 '
b01011111 .
#5
0#
#6
1#
b001011100 '
b01011100 .
#7
0#
#8
1#
#9
0#
#10
1#
b001011001 '
b01011001 .
#11
0#
#12
1#
b001011011 '
b01011011 .
#13
0#
#14
1#
b001011101 '
b01011101 .
#15
0#
#16
1#
b001100000 '
b01100000 .
#17
0#
#18
1#
b001100101 '
b01100101 .
#19
0#
#20
1#
b001101010 '
b01101010 .
#21
0#
#22
1#
b001110000 '
b01110000 .
#23
0#
#24
1#
b001110011 '
b01110011 .
#25
0#
#26
1#
b001111011 '
b01111011 .
#27
0#
#28
1#
b010000000 '
b10000000 .
#29
0#
#30
1#
b001111111 '
b01111111 .
#31
0#
#32
1#
b010000000 '
b10000000 .
#33
0#
#34
1#
b010000001 '
b10000001 .
#35
0#
#36
1#
b001111110 '
b01111110 .
#37
0#
#38
1#
b001110111 '
b01110111 .
#39
0#
#40
1#
b001110110 '
b01110110 .
#41
0#
#42
1#
b001101111 '
b01101111 .
#43
0#
#44
1#
b001101010 '
b01101010 .
#45
0#
#46
1#
b001100100 '
b01100100 .
#47
0#
#48
1#
b001011111 '
b01011111 .
#49
0#
#50
1#
b001011010 '
b01011010 .
#51
0#
#52
1#
b001011000 '
b01011000 .
#53
0#
#54
1#
b001010110 '
b01010110 .
#55
0#
#56
1#
b001011000 '
b01011000 .
#57
0#
#58
1#
b001010111 '
b01010111 .
#59
0#
#60
1#
b001011010 '
b01011010 .
#61
0#
#62
1#
b001100001 '
b01100001 .
#63
0#
#64
1#
b001100111 '
b01100111 .
#65
0#
#66
1#
b001101011 '
b01101011 .
#67
0#
#68
1#
b001110001 '
b01110001 .
#69
0#
#70
1#
b001110101 '
b01110101 .
#71
0#
#72
1#
b001111000 '
b01111000 .
#73
0#
#74
1#
b001111101 '
b01111101 .
#75
0#
#76
1#
#77
0#
#78
1#
#79
0#
#80
1#
b001111011 '
b01111011 .
#81
0#
#82
1#
b001111000 '
b01111000 .
#83
0#
#84
1#
b001110011 '
b01110011 .
#85
0#
#86
1#
b001101111 '
b01101111 .
#87
0#
#88
1#
b001101010 '
b01101010 .
#89
0#
#90
1#
b001100101 '
b01100101 .
#91
0#
#92
1#
b001100000 '
b01100000 .
#93
0#
#94
1#
b001011101 '
b01011101 .
#95
0#
#96
1#
b001011011 '
b01011011 .
#97
0#
#98
1#
#99
0#
#100
1#
b001011101 '
b01011101 .
#101
0#
#102
1#
b001011111 '
b01011111 .
#103
0#
#104
1#
b001100010 '
b01100010 .
#105
0#
#106
1#
b001101000 '
b01101000 .
#107
0#
#108
1#
b001101101 '
b01101101 .
#109
0#
#110
1#
b001110011 '
b01110011 .
#111
0#
#112
1#
b001111000 '
b01111000 .
#113
0#
#114
1#
b001111010 '
b01111010 .
#115
0#
#116
1#
b001111100 '
b01111100 .
#117
0#
#118
1#
b010000000 '
b10000000 .
#119
0#
#120
1#
b001111111 '
b01111111 .
#121
0#
#122
1#
b001111101 '
b01111101 .
#123
0#
#124
1#
b001111001 '
b01111001 .
#125
0#
#126
1#
b001110100 '
b01110100 .
#127
0#
#128
1#
b001110000 '
b01110000 .
#129
0#
#130
1#
b001101011 '
b01101011 .
#131
0#
#132
1#
b001100010 '
b01100010 .
#133
0#
#134
1#
b001011110 '
b01011110 .
#135
0#
#136
1#
b001011001 '
b01011001 .
#137
0#
#138
1#
b001010111 '
b01010111 .
#139
0#
#140
1#
b001011000 '
b01011000 .
#141
0#
#142
1#
b001010110 '
b01010110 .
#143
0#
#144
1#
b001010111 '
b01010111 .
#145
0#
#146
1#
b001011000 '
b01011000 .
#147
0#
#148
1#
b001011101 '
b01011101 .
#149
0#
#150
1#
b001100010 '
b01100010 .
#151
0#
#152
1#
b001101001 '
b01101001 .
#153
0#
#154
1#
b001101111 '
b01101111 .
#155
0#
#156
1#
b001110101 '
b01110101 .
#157
0#
#158
1#
b001110110 '
b01110110 .
#159
0#
#160
1#
b001111011 '
b01111011 .
#161
0#
#162
1#
b001111110 '
b01111110 .
#163
0#
#164
1#
b001111100 '
b01111100 .
#165
0#
#166
1#
b001111010 '
b01111010 .
#167
0#
#168
1#
b001111000 '
b01111000 .
#169
0#
#170
1#
#171
0#
#172
1#
b001110010 '
b01110010 .
#173
0#
#174
1#
b001101011 '
b01101011 .
#175
0#
#176
1#
b001101000 '
b01101000 .
#177
0#
#178
1#
b001100100 '
b01100100 .
#179
0#
#180
1#
b001100000 '
b01100000 .
#181
0#
#182
1#
b001011110 '
b01011110 .
#183
0#
#184
1#
#185
0#
#186
1#
b001011100 '
b01011100 .
#187
0#
#188
1#
b001011110 '
b01011110 .
#189
0#
#190
1#
b001100100 '
b01100100 .
#191
0#
#192
1#
b001100110 '
b01100110 .
#193
0#
#194
1#
b001101011 '
b01101011 .
#195
0#
#196
1#
b001101110 '
b01101110 .
#197
0#
#198
1#
b001110100 '
b01110100 .
#199
0#
#200
1#
b001111000 '
b01111000 .
#201
0#
#202
1#
b001111011 '
b01111011 .
#203
0#
#204
1#
b001111110 '
b01111110 .
#205
0#
#206
1#
b001111011 '
b01111011 .
#207
0#
#208
1#
#209
0#
#210
1#
b001111010 '
b01111010 .
#211
0#
#212
1#
b001110011 '
b01110011 .
#213
0#
#214
1#
b001101110 '
b01101110 .
#215
0#
#216
1#
b001101010 '
b01101010 .
#217
0#
#218
1#
b001100110 '
b01100110 .
#219
0#
#220
1#
b001011110 '
b01011110 .
#221
0#
#222
1#
b001011100 '
b01011100 .
#223
0#
#224
1#
b001011000 '
b01011000 .
#225
0#
#226
1#
b001011001 '
b01011001 .
#227
0#
#228
1#
b001010110 '
b01010110 .
#229
0#
#230
1#
b001011011 '
b01011011 .
#231
0#
#232
1#
#233
0#
#234
1#
b001011110 '
b01011110 .
#235
0#
#236
1#
b001100101 '
b01100101 .
#237
0#
#238
1#
b001101010 '
b01101010 .
#239
0#
#240
1#
b001101011 '
b01101011 .
#241
0#
#242
1#
b001101101 '
b01101101 .
#243
0#
#244
1#
b001101011 '
b01101011 .
#245
0#
#246
1#
#247
0#
#248
1#
#249
0#
#250
1#
b001101001 '
b01101001 .
#251
0#
#252
1#
b001101100 '
b01101100 .
#253
0#
#254
1#
b001101011 '
b01101011 .
#255
0#
#256
1#
b001101010 '
b01101010 .
#257
0#
#258
1#
#259
0#
#260
1#
b001101011 '
b01101011 .
#261
0#
#262
1#
b001101100 '
b01101100 .
#263
0#
#264
1#
b001101001 '
b01101001 .
#265
0#
#266
1#
b001101011 '
b01101011 .
#267
0#
#268
1#
b001101001 '
b01101001 .
#269
0#
#270
1#
#271
0#
#272
1#
b001101011 '
b01101011 .
#273
0#
#274
1#
b001101001 '
b01101001 .
#275
0#
#276
1#
#277
0#
#278
1#
b001101010 '
b01101010 .
#279
0#
#280
1#
#281
0#
#282
1#
b001101001 '
b01101001 .
#283
0#
#284
1#
b001101010 '
b01101010 .
#285
0#
#286
1#
b001101001 '
b01101001 .
#287
0#
#288
1#
b001101011 '
b01101011 .
#289
0#
#290
1#
b001101001 '
b01101001 .
#291
0#
#292
1#
b001101011 '
b01101011 .
#293
0#
#294
1#
b001101100 '
b01101100 .
#295
0#
#296
1#
b001101011 '
b01101011 .
#297
0#
#298
1#
#299
0#
#300
1#
b001101100 '
b01101100 .
#301
0#
#302
1#
b001101011 '
b01101011 .
#303
0#
#304
1#
#305
0#
#306
1#
#307
0#
#308
1#
b001101100 '
b01101100 .
#309
0#
#310
1#
b001101001 '
b01101001 .
#311
0#
#312
1#
b001101010 '
b01101010 .
#313
0#
#314
1#
b001101011 '
b01101011 .
#315
0#
#316
1#
b001101100 '
b01101100 .
#317
0#
#318
1#
b001101011 '
b01101011 .
#319
0#
#320
1#
b001101010 '
b01101010 .
#321
0#
#322
1#
#323
0#
#324
1#
#325
0#
#326
1#
b001101011 '
b01101011 .
#327
0#
#328
1#
b001101100 '
b01101100 .
#329
0#
#330
1#
#331
0#
#332
1#
b001101010 '
b01101010 .
#333
0#
#334
1#
b001101011 '
b01101011 .
#335
0#
#336
1#
b001101100 '
b01101100 .
#337
0#
#338
1#
#339
0#
#340
1#
b001101010 '
b01101010 .
#341
0#
#342
1#
b001101101 '
b01101101 .
#343
0#
#344
1#
b001101011 '
b01101011 .
#345
0#
#346
1#
#347
0#
#348
1#
b001101101 '
b01101101 .
#349
0#
#350
1#
b001101011 '
b01101011 .
#351
0#
#352
1#
b001101100 '
b01101100 .
#353
0#
#354
1#
b001101110 '
b01101110 .
#355
0#
#356
1#
b001101101 '
b01101101 .
#357
0#
#358
1#
b001101100 '
b01101100 .
#359
0#
#360
1#
b001101011 '
b01101011 .
#361
0#
#362
1#
b001101100 '
b01101100 .
#363
0#
#364
1#
b001101101 '
b01101101 .
#365
0#
#366
1#
b001101100 '
b01101100 .
#367
0#
#368
1#
b001101011 '
b01101011 .
#369
0#
#370
1#
b001101101 '
b01101101 .
#371
0#
#372
1#
b001101011 '
b01101011 .
#373
0#
#374
1#
#375
0#
#376
1#
b001101001 '
b01101001 .
#377
0#
#378
1#
b001101101 '
b01101101 .
#379
0#
#380
1#
#381
0#
#382
1#
b001101100 '
b01101100 .
#383
0#
#384
1#
#385
0#
#386
1#
b001101011 '
b01101011 .
#387
0#
#388
1#
b001101101 '
b01101101 .
#389
0#
#390
1#
b001101100 '
b01101100 .
#391
0#
#392
1#
b001101011 '
b01101011 .
#393
0#
#394
1#
b001101101 '
b01101101 .
#395
0#
#396
1#
#397
0#
#398
1#
b001101011 '
b01101011 .
#399
0#
#400
1#
#401
0#
#402
1#
#403
0#
#404
1#
b001101100 '
b01101100 .
#405
0#
#406
1#
#407
0#
#408
1#
#409
0#
#410
1#
#411
0#
#412
1#
b001101011 '
b01101011 .
#413
0#
#414
1#
b001101110 '
b01101110 .
#415
0#
#416
1#
b001101111 '
b01101111 .
#417
0#
#418
1#
b001101100 '
b01101100 .
#419
0#
#420
1#
b001101110 '
b01101110 .
#421
0#
#422
1#
b001101011 '
b01101011 .
#423
0#
#424
1#
b001101010 '
b01101010 .
#425
0#
#426
1#
b001101110 '
b01101110 .
#427
0#
#428
1#
b001101011 '
b01101011 .
#429
0#
#430
1#
b001101110 '
b01101110 .
#431
0#
#432
1#
b001101100 '
b01101100 .
#433
0#
#434
1#
#435
0#
#436
1#
b001101011 '
b01101011 .
#437
0#
#438
1#
b001101101 '
b01101101 .
#439
0#
#440
1#
#441
0#
#442
1#
b001101010 '
b01101010 .
#443
0#
#444
1#
b001101100 '
b01101100 .
#445
0#
#446
1#
b001101101 '
b01101101 .
#447
0#
#448
1#
b001101110 '
b01101110 .
#449
0#
#450
1#
b001101011 '
b01101011 .
#451
0#
#452
1#
b001101100 '
b01101100 .
#453
0#
#454
1#
b001101101 '
b01101101 .
#455
0#
#456
1#
b001101010 '
b01101010 .
#457
0#
#458
1#
b001101011 '
b01101011 .
#459
0#
#460
1#
b001101010 '
b01101010 .
#461
0#
#462
1#
#463
0#
#464
1#
#465
0#
#466
1#
b001101011 '
b01101011 .
#467
0#
#468
1#
#469
0#
#470
1#
b001101010 '
b01101010 .
#471
0#
#472
1#
b001101011 '
b01101011 .
#473
0#
#474
1#
#475
0#
#476
1#
b001101100 '
b01101100 .
#477
0#
#478
1#
#479
0#
#480
1#
b001101110 '
b01101110 .
#481
0#
#482
1#
b001101010 '
b01101010 .
#483
0#
#484
1#
b001101000 '
b01101000 .
#485
0#
#486
1#
b001101100 '
b01101100 .
#487
0#
#488
1#
b001101010 '
b01101010 .
#489
0#
#490
1#
b001101101 '
b01101101 .
#491
0#
#492
1#
b001101100 '
b01101100 .
#493
0#
#494
1#
#495
0#
#496
1#
b001101011 '
b01101011 .
#497
0#
#498
1#
b001101100 '
b01101100 .
#499
0#
#500
1#
#501
0#
#502
1#
#503
0#
#504
1#
b001101101 '
b01101101 .
#505
0#
#506
1#
b001101100 '
b01101100 .
#507
0#
#508
1#
b001101011 '
b01101011 .
#509
0#
#510
1#
#511
0#
#512
1#
#513
0#
#514
1#
#515
0#
#516
1#
b001101100 '
b01101100 .
#517
0#
#518
1#
#519
0#
#520
1#
b001101011 '
b01101011 .
#521
0#
#522
1#
b001101010 '
b01101010 .
#523
0#
#524
1#
#525
0#
#526
1#
b001101000 '
b01101000 .
#527
0#
#528
1#
b001101011 '
b01101011 .
#529
0#
#530
1#
b001101010 '
b01101010 .
#531
0#
#532
1#
b001101011 '
b01101011 .
#533
0#
#534
1#
b001101010 '
b01101010 .
#535
0#
#536
1#
b001101011 '
b01101011 .
#537
0#
#538
1#
b001101010 '
b01101010 .
#539
0#
#540
1#
b001101011 '
b01101011 .
#541
0#
#542
1#
#543
0#
#544
1#
b001101101 '
b01101101 .
#545
0#
#546
1#
b001101100 '
b01101100 .
#547
0#
#548
1#
b001101011 '
b01101011 .
#549
0#
#550
1#
b001101010 '
b01101010 .
#551
0#
#552
1#
b001101110 '
b01101110 .
#553
0#
#554
1#
b001101011 '
b01101011 .
#555
0#
#556
1#
b001101010 '
b01101010 .
#557
0#
#558
1#
b001101100 '
b01101100 .
#559
0#
#560
1#
b001101011 '
b01101011 .
#561
0#
#562
1#
b001101100 '
b01101100 .
#563
0#
#564
1#
#565
0#
#566
1#
b001101010 '
b01101010 .
#567
0#
#568
1#
b001101100 '
b01101100 .
#569
0#
#570
1#
b001101011 '
b01101011 .
#571
0#
#572
1#
#573
0#
#574
1#
b001101100 '
b01101100 .
#575
0#
#576
1#
b001101001 '
b01101001 .
#577
0#
#578
1#
b001101011 '
b01101011 .
#579
0#
#580
1#
b001101101 '
b01101101 .
#581
0#
#582
1#
b001101011 '
b01101011 .
#583
0#
#584
1#
b001101101 '
b01101101 .
#585
0#
#586
1#
#587
0#
#588
1#
b001101010 '
b01101010 .
#589
0#
#590
1#
b001101100 '
b01101100 .
#591
0#
#592
1#
b001101011 '
b01101011 .
#593
0#
#594
1#
#595
0#
#596
1#
b001101110 '
b01101110 .
#597
0#
#598
1#
b001101010 '
b01101010 .
#599
0#
#600
1#
b001101100 '
b01101100 .
#601
0#
#602
1#
#603
0#
#604
1#
b001101010 '
b01101010 .
#605
0#
#606
1#
b001101011 '
b01101011 .
#607
0#
#608
1#
b001101010 '
b01101010 .
#609
0#
#610
1#
b001101001 '
b01101001 .
#611
0#
#612
1#
b001101011 '
b01101011 .
#613
0#
#614
1#
b001101101 '
b01101101 .
#615
0#
#616
1#
b001101001 '
b01101001 .
#617
0#
#618
1#
b001101011 '
b01101011 .
#619
0#
#620
1#
#621
0#
#622
1#
b001101100 '
b01101100 .
#623
0#
#624
1#
b001101010 '
b01101010 .
#625
0#
#626
1#
b001101100 '
b01101100 .
#627
0#
#628
1#
#629
0#
#630
1#
b001101101 '
b01101101 .
#631
0#
#632
1#
b001101100 '
b01101100 .
#633
0#
#634
1#
b001101011 '
b01101011 .
#635
0#
#636
1#
b001101101 '
b01101101 .
#637
0#
#638
1#
#639
0#
#640
1#
b001101011 '
b01101011 .
#641
0#
#642
1#
b001101100 '
b01101100 .
#643
0#
#644
1#
b001101010 '
b01101010 .
#645
0#
#646
1#
b001101011 '
b01101011 .
#647
0#
#648
1#
b001101001 '
b01101001 .
#649
0#
#650
1#
b001101101 '
b01101101 .
#651
0#
#652
1#
b001101011 '
b01101011 .
#653
0#
#654
1#
b001101110 '
b01101110 .
#655
0#
#656
1#
b001101100 '
b01101100 .
#657
0#
#658
1#
b001101011 '
b01101011 .
#659
0#
#660
1#
b001101000 '
b01101000 .
#661
0#
#662
1#
b001101010 '
b01101010 .
#663
0#
#664
1#
b001101011 '
b01101011 .
#665
0#
#666
1#
#667
0#
#668
1#
#669
0#
#670
1#
b001101010 '
b01101010 .
#671
0#
#672
1#
b001101011 '
b01101011 .
#673
0#
#674
1#
b001101010 '
b01101010 .
#675
0#
#676
1#
b001101100 '
b01101100 .
#677
0#
#678
1#
b001101011 '
b01101011 .
#679
0#
#680
1#
#681
0#
#682
1#
b001101001 '
b01101001 .
#683
0#
#684
1#
b001101010 '
b01101010 .
#685
0#
#686
1#
#687
0#
#688
1#
b001101001 '
b01101001 .
#689
0#
#690
1#
b001101011 '
b01101011 .
#691
0#
#692
1#
#693
0#
#694
1#
b001101010 '
b01101010 .
#695
0#
#696
1#
b001101011 '
b01101011 .
#697
0#
#698
1#
b001101010 '
b01101010 .
#699
0#
#700
1#
b001101011 '
b01101011 .
#701
0#
#702
1#
b001101001 '
b01101001 .
#703
0#
#704
1#
b001101011 '
b01101011 .
#705
0#
#706
1#
b001101100 '
b01101100 .
#707
0#
#708
1#
#709
0#
#710
1#
b001101011 '
b01101011 .
#711
0#
#712
1#
b001101010 '
b01101010 .
#713
0#
#714
1#
b001101100 '
b01101100 .
#715
0#
#716
1#
#717
0#
#718
1#
b001101010 '
b01101010 .
#719
0#
#720
1#
b001101110 '
b01101110 .
#721
0#
#722
1#
b001101011 '
b01101011 .
#723
0#
#724
1#
b001101100 '
b01101100 .
#725
0#
#726
1#
b001101110 '
b01101110 .
#727
0#
#728
1#
b001101011 '
b01101011 .
#729
0#
#730
1#
b001101101 '
b01101101 .
#731
0#
#732
1#
b001101010 '
b01101010 .
#733
0#
#734
1#
b001101011 '
b01101011 .
#735
0#
#736
1#
#737
0#
#738
1#
b001101110 '
b01101110 .
#739
0#
#740
1#
b001101100 '
b01101100 .
#741
0#
#742
1#
b001101011 '
b01101011 .
#743
0#
#744
1#
b001101100 '
b01101100 .
#745
0#
#746
1#
b001101110 '
b01101110 .
#747
0#
#748
1#
b001101100 '
b01101100 .
#749
0#
#750
1#
#751
0#
#752
1#
#753
0#
#754
1#
#755
0#
#756
1#
b001101010 '
b01101010 .
#757
0#
#758
1#
b001101101 '
b01101101 .
#759
0#
#760
1#
b001101100 '
b01101100 .
#761
0#
#762
1#
b001101101 '
b01101101 .
#763
0#
#764
1#
#765
0#
#766
1#
b001101011 '
b01101011 .
#767
0#
#768
1#
#769
0#
#770
1#
#771
0#
#772
1#
b001101100 '
b01101100 .
#773
0#
#774
1#
#775
0#
#776
1#
#777
0#
#778
1#
#779
0#
#780
1#
b001101011 '
b01101011 .
#781
0#
#782
1#
b001101100 '
b01101100 .
#783
0#
#784
1#
b001101011 '
b01101011 .
#785
0#
#786
1#
#787
0#
#788
1#
b001101110 '
b01101110 .
#789
0#
#790
1#
b001101100 '
b01101100 .
#791
0#
#792
1#
b001101011 '
b01101011 .
#793
0#
#794
1#
b001101100 '
b01101100 .
#795
0#
#796
1#
b001101010 '
b01101010 .
#797
0#
#798
1#
b001101100 '
b01101100 .
#799
0#
#800
1#
#801
0#
#802
1#
#803
0#
#804
1#
#805
0#
#806
1#
b001101010 '
b01101010 .
#807
0#
#808
1#
b001101100 '
b01101100 .
#809
0#
#810
1#
b001101011 '
b01101011 .
#811
0#
#812
1#
b001101101 '
b01101101 .
#813
0#
#814
1#
#815
0#
#816
1#
b001101100 '
b01101100 .
#817
0#
#818
1#
b001101101 '
b01101101 .
#819
0#
#820
1#
b001101100 '
b01101100 .
#821
0#
#822
1#
b001101101 '
b01101101 .
#823
0#
#824
1#
b001101011 '
b01101011 .
#825
0#
#826
1#
b001101010 '
b01101010 .
#827
0#
#828
1#
b001101001 '
b01101001 .
#829
0#
#830
1#
b001101101 '
b01101101 .
#831
0#
#832
1#
b001101100 '
b01101100 .
#833
0#
#834
1#
b001101001 '
b01101001 .
#835
0#
#836
1#
b001101100 '
b01101100 .
#837
0#
#838
1#
b001101010 '
b01101010 .
#839
0#
#840
1#
#841
0#
#842
1#
b001101101 '
b01101101 .
#843
0#
#844
1#
b001101011 '
b01101011 .
#845
0#
#846
1#
b001101100 '
b01101100 .
#847
0#
#848
1#
#849
0#
#850
1#
b001101101 '
b01101101 .
#851
0#
#852
1#
b001101100 '
b01101100 .
#853
0#
#854
1#
b001101011 '
b01101011 .
#855
0#
#856
1#
#857
0#
#858
1#
b001101100 '
b01101100 .
#859
0#
#860
1#
b001101010 '
b01101010 .
#861
0#
#862
1#
#863
0#
#864
1#
b001101100 '
b01101100 .
#865
0#
#866
1#
b001101010 '
b01101010 .
#867
0#
#868
1#
b001101100 '
b01101100 .
#869
0#
#870
1#
b001101001 '
b01101001 .
#871
0#
#872
1#
b001101010 '
b01101010 .
#873
0#
#874
1#
b001101011 '
b01101011 .
#875
0#
#876
1#
b001101001 '
b01101001 .
#877
0#
#878
1#
b001101010 '
b01101010 .
#879
0#
#880
1#
b001101011 '
b01101011 .
#881
0#
#882
1#
#883
0#
#884
1#
#885
0#
#886
1#
b001101001 '
b01101001 .
#887
0#
#888
1#
b001101011 '
b01101011 .
#889
0#
#890
1#
b001101101 '
b01101101 .
#891
0#
#892
1#
b001101010 '
b01101010 .
#893
0#
#894
1#
b001101011 '
b01101011 .
#895
0#
#896
1#
b001101001 '
b01101001 .
#897
0#
#898
1#
b001101010 '
b01101010 .
#899
0#
#900
1#
b001101100 '
b01101100 .
#901
0#
#902
1#
b001101101 '
b01101101 .
#903
0#
#904
1#
b001101111 '
b01101111 .
#905
0#
#906
1#
b001101011 '
b01101011 .
#907
0#
#908
1#
b001101010 '
b01101010 .
#909
0#
#910
1#
b001101011 '
b01101011 .
#911
0#
#912
1#
#913
0#
#914
1#
#915
0#
#916
1#
b001101100 '
b01101100 .
#917
0#
#918
1#
b001101101 '
b01101101 .
#919
0#
#920
1#
b001101100 '
b01101100 .
#921
0#
#922
1#
b001101101 '
b01101101 .
#923
0#
#924
1#
b001101011 '
b01101011 .
#925
0#
#926
1#
b001101100 '
b01101100 .
#927
0#
#928
1#
b001101011 '
b01101011 .
#929
0#
#930
1#
b001101100 '
b01101100 .
#931
0#
#932
1#
b001101011 '
b01101011 .
#933
0#
#934
1#
#935
0#
#936
1#
b001101100 '
b01101100 .
#937
0#
#938
1#
b001101011 '
b01101011 .
#939
0#
#940
1#
b001101101 '
b01101101 .
#941
0#
#942
1#
b001101100 '
b01101100 .
#943
0#
#944
1#
b001101011 '
b01101011 .
#945
0#
#946
1#
#947
0#
#948
1#
#949
0#
#950
1#
b001101010 '
b01101010 .
#951
0#
#952
1#
b001101100 '
b01101100 .
#953
0#
#954
1#
b001101001 '
b01101001 .
#955
0#
#956
1#
b001101010 '
b01101010 .
#957
0#
#958
1#
b001101011 '
b01101011 .
#959
0#
#960
1#
#961
0#
#962
1#
#963
0#
#964
1#
b001101001 '
b01101001 .
#965
0#
#966
1#
b001101010 '
b01101010 .
#967
0#
#968
1#
b001101000 '
b01101000 .
#969
0#
#970
1#
b001101010 '
b01101010 .
#971
0#
#972
1#
b001101011 '
b01101011 .
#973
0#
#974
1#
b001101010 '
b01101010 .
#975
0#
#976
1#
b001101100 '
b01101100 .
#977
0#
#978
1#
b001101011 '
b01101011 .
#979
0#
#980
1#
b001100111 '
b01100111 .
#981
0#
#982
1#
b001101010 '
b01101010 .
#983
0#
#984
1#
#985
0#
#986
1#
b001101011 '
b01101011 .
#987
0#
#988
1#
b001101001 '
b01101001 .
#989
0#
#990
1#
b001101100 '
b01101100 .
#991
0#
#992
1#
b001101011 '
b01101011 .
#993
0#
#994
1#
b001101001 '
b01101001 .
#995
0#
#996
1#
#997
0#
#998
1#
b001101010 '
b01101010 .
#999
0#
#1000
1#
b001101100 '
b01101100 .
#1001
0#
#1002
1#
b001101011 '
b01101011 .
#1003
0#
#1004
1#
b001101100 '
b01101100 .
#1005
0#
#1006
1#
b001101011 '
b01101011 .
#1007
0#
#1008
1#
b001101100 '
b01101100 .
#1009
0#
#1010
1#
b001101011 '
b01101011 .
#1011
0#
#1012
1#
b001101001 '
b01101001 .
#1013
0#
#1014
1#
b001101011 '
b01101011 .
#1015
0#
#1016
1#
b001101010 '
b01101010 .
#1017
0#
#1018
1#
b001101011 '
b01101011 .
#1019
0#
#1020
1#
#1021
0#
#1022
1#
#1023
0#
#1024
1#
#1025
0#
#1026
1#
b001111001 '
b01111001 .
#1027
0#
#1028
1#
b001101011 '
b01101011 .
#1029
0#
#1030
1#
b001110100 '
b01110100 .
#1031
0#
#1032
1#
b001110011 '
b01110011 .
#1033
0#
#1034
1#
b001101100 '
b01101100 .
#1035
0#
#1036
1#
b001100111 '
b01100111 .
#1037
0#
#1038
1#
b001101010 '
b01101010 .
#1039
0#
#1040
1#
b001101111 '
b01101111 .
#1041
0#
#1042
1#
b001101011 '
b01101011 .
#1043
0#
#1044
1#
b001100011 '
b01100011 .
#1045
0#
#1046
1#
b001101000 '
b01101000 .
#1047
0#
#1048
1#
b001101011 '
b01101011 .
#1049
0#
#1050
1#
b001101000 '
b01101000 .
#1051
0#
#1052
1#
b001101011 '
b01101011 .
#1053
0#
#1054
1#
#1055
0#
#1056
1#
b001101100 '
b01101100 .
#1057
0#
#1058
1#
b001110000 '
b01110000 .
#1059
0#
#1060
1#
b001110011 '
b01110011 .
#1061
0#
#1062
1#
b001101100 '
b01101100 .
#1063
0#
#1064
1#
b001110100 '
b01110100 .
#1065
0#
#1066
1#
b001101101 '
b01101101 .
#1067
0#
#1068
1#
b001101111 '
b01101111 .
#1069
0#
#1070
1#
b001101100 '
b01101100 .
#1071
0#
#1072
1#
b001110100 '
b01110100 .
#1073
0#
#1074
1#
b001101010 '
b01101010 .
#1075
0#
#1076
1#
b001110000 '
b01110000 .
#1077
0#
#1078
1#
b001101011 '
b01101011 .
#1079
0#
#1080
1#
b001100101 '
b01100101 .
#1081
0#
#1082
1#
b001101100 '
b01101100 .
#1083
0#
#1084
1#
b001101000 '
b01101000 .
#1085
0#
#1086
1#
#1087
0#
#1088
1#
#1089
0#
#1090
1#
b001100110 '
b01100110 .
#1091
0#
#1092
1#
b001100111 '
b01100111 .
#1093
0#
#1094
1#
b001101001 '
b01101001 .
#1095
0#
#1096
1#
b001100111 '
b01100111 .
#1097
0#
#1098
1#
b001101101 '
b01101101 .
#1099
0#
#1100
1#
b001101001 '
b01101001 .
#1101
0#
#1102
1#
b001101100 '
b01101100 .
#1103
0#
#1104
1#
b001110000 '
b01110000 .
#1105
0#
